pressiolinalg/__init__.py
pressiolinalg/linalg.py
pressiolinalg/test_utils.py
pressiolinalg/utils.py
pressio_linalg-0.1.0rc7.dist-info/METADATA
pressio_linalg-0.1.0rc7.dist-info/WHEEL
pressio_linalg-0.1.0rc7.dist-info/top_level.txt
pressio_linalg-0.1.0rc7.dist-info/RECORD
