Metadata-Version: 2.1
Name: pressio-linalg
Version: 0.1.0rc7
Summary: Parallel linear algebra library
Author-email: francesco.rizzi@ng-analytics.com
Keywords: model reduction,scientific computing,dense linear algebra,parallel computing,hyper-reduction,HPC
Classifier: License :: OSI Approved :: BSD License
Classifier: Operating System :: Unix
Classifier: Environment :: MacOS X
Classifier: Programming Language :: C++
Classifier: Programming Language :: Python :: 3 :: Only
Classifier: Topic :: Scientific/Engineering
Classifier: Topic :: Scientific/Engineering :: Mathematics
Classifier: Topic :: Scientific/Engineering :: Physics
Classifier: Topic :: Software Development :: Libraries
Classifier: Development Status :: 4 - Beta
Requires-Python: >=3
Requires-Dist: numpy
Requires-Dist: scipy
Requires-Dist: pytest-mpi
Requires-Dist: pytest
